{
 "license_type": 1,
 "fp_ref_id": "0e8e70fc464e2efa",
 "is_new_track": false,
 "mood": "Inspirational",
 "popularity_percentile": 99,
 "track_url": "",
 "category": "",
 "display_category": "",
 "downloadable": true,
 "waveform_url": "https://www.youtube.com/api/editor/waveform?expire=1579467600&if=0&scale=10&editlist=Cgh3YXZlZm9ybRocCOjvBxIWChAwZThlNzBmYzQ2NGUyZWZhEAAYAg%3D%3D&sigh=0dkkNAcWDgaieArZPtg_1w",
 "download_url": "https://www.youtube.com/audiolibrary_download?vid=0e8e70fc464e2efa",
 "artist": "Verified Picasso",
 "len": 129,
 "streamid": "yknZ9NYIucpwu6V18J1WHIGvsZKfqZlMBRfmhCYgMpbCgOyYMqfNoHMrzknIsYWx",
 "album": "None",
 "display_mood": "Inspirational",
 "instruments": [
  "synth",
  "drums",
  "bass",
  "808",
  "piano"
 ],
 "genre": "Dance & Electronic",
 "display_genre": "Dance & Electronic",
 "title": "Socialite Mugshot",
 "vid": "0e8e70fc464e2efa",
 "reference_vid": "0e8e70fc464e2efa",
 "artist_channel_url": "/channel/UCqDmyXPJdrZjwUdWLyhyQRA",
 "favorite": false,
 "artist_url": "https://www.youtube.com/channel/UCqDmyXPJdrZjwUdWLyhyQRA"
}