{
 "license_type": 6,
 "len": 90.583,
 "track_url": "http://incompetech.com/music/royalty-free/index.html?isrc=USUAN1100471",
 "is_new_track": false,
 "category": "",
 "reference_vid": "112d7477abc0efc3",
 "mood": "Dark",
 "display_mood": "Dark",
 "artist": "Kevin MacLeod",
 "downloadable": true,
 "waveform_url": "https://www.youtube.com/api/editor/waveform?expire=1579467600&if=0&scale=10&editlist=Cgh3YXZlZm9ybRocCJC_BRIWChAxMTJkNzQ3N2FiYzBlZmMzEAAYAg%3D%3D&sigh=moiJCWq23OuHu01efJ_6mg",
 "album": "None",
 "download_url": "https://www.youtube.com/audiolibrary_download?vid=112d7477abc0efc3",
 "streamid": "FF2Sg0oxfjaj1m9mRKulOTGgCtcaenB7m6k_I-3JXc_d5i4iF3fwhTPUhP1Y-QGi",
 "title": "Classic Horror 1 - Dark World",
 "display_genre": "Cinematic",
 "artist_channel_url": null,
 "instruments": [
  "Piano"
 ],
 "vid": "112d7477abc0efc3",
 "artist_url": "http://incompetech.com/",
 "genre": "Cinematic",
 "popularity_percentile": 40,
 "fp_ref_id": "112d7477abc0efc3",
 "display_category": "",
 "favorite": false
}