{
 "license_type": 1,
 "fp_ref_id": "138eeba447969f75",
 "is_new_track": false,
 "mood": "Romantic",
 "popularity_percentile": 99,
 "track_url": "",
 "category": "",
 "display_category": "",
 "downloadable": true,
 "waveform_url": "https://www.youtube.com/api/editor/waveform?expire=1579460400&if=0&scale=10&editlist=Cgh3YXZlZm9ybRocCOC5DBIWChAxMzhlZWJhNDQ3OTY5Zjc1EAAYAg%3D%3D&sigh=KuHvZN9eSOwdnIcPG11wCg",
 "download_url": "https://www.youtube.com/audiolibrary_download?vid=138eeba447969f75",
 "artist": "Asher Fulero",
 "len": 204,
 "streamid": "fAOMoQpE-LxOYhgZmQSr76_auwrzrhaniU04Yw6hdOol1NKo7teMfX1Cw1-apdTQ",
 "album": "None",
 "display_mood": "Romantic",
 "instruments": [
  "acoustic guitar",
  "piano synth",
  "organ",
  "bass drum"
 ],
 "genre": "Dance & Electronic",
 "display_genre": "Dance & Electronic",
 "title": "Lusciousness",
 "vid": "138eeba447969f75",
 "reference_vid": "138eeba447969f75",
 "artist_channel_url": "/channel/UCKn6_1iFFC5fxSmFgVC9Fsw",
 "favorite": false,
 "artist_url": ""
}