{
 "album": "None",
 "category": "",
 "popularity_percentile": 99,
 "mood": "Dramatic",
 "artist_url": "https://www.youtube.com/channel/UCL1zFMJb0sthwdAlGjGbdyg",
 "is_new_track": false,
 "track_url": "",
 "reference_vid": "1831559ba7f189d7",
 "display_category": "",
 "fp_ref_id": "1831559ba7f189d7",
 "download_url": "https://www.youtube.com/audiolibrary_download?vid=1831559ba7f189d7",
 "artist_channel_url": "/channel/UCL1zFMJb0sthwdAlGjGbdyg",
 "downloadable": true,
 "display_genre": "Rock",
 "title": "Reverie",
 "favorite": false,
 "license_type": 1,
 "len": 229,
 "display_mood": "Dramatic",
 "instruments": [],
 "waveform_url": "https://www.youtube.com/api/editor/waveform?expire=1579467600&if=0&scale=10&editlist=Cgh3YXZlZm9ybRocCIj9DRIWChAxODMxNTU5YmE3ZjE4OWQ3EAAYAg%3D%3D&sigh=MKQAVv72AxmroVmxePL--g",
 "streamid": "8qTy62-Bw7mz7UvielzNZV1VAsunWReSOvivj0uKkbmN4DFLyzIyUI44roUnYWBD",
 "genre": "Rock",
 "vid": "1831559ba7f189d7",
 "artist": "Quincas Moreira"
}