{
 "track_url": "",
 "download_url": "https://www.youtube.com/audiolibrary_download?vid=23c404ebcee1652c",
 "downloadable": true,
 "reference_vid": "23c404ebcee1652c",
 "mood": "Sad",
 "artist_url": "https://www.youtube.com/channel/UCnJoBJAmgihRWlyV5QgSujA",
 "license_type": 1,
 "len": 138,
 "instruments": [
  "electric guitar"
 ],
 "favorite": false,
 "waveform_url": "https://www.youtube.com/api/editor/waveform?expire=1579460400&if=0&scale=10&editlist=Cgh3YXZlZm9ybRocCJC2CBIWChAyM2M0MDRlYmNlZTE2NTJjEAAYAg%3D%3D&sigh=Tx7TLlLaRPNFQ7EARwsvbQ",
 "streamid": "RfSmNlRlRN38RrBD4z3Q1e_mkz4_HrM2SZfFNY-i4_eUaxV1OoY4KlU-qHQ_v4Mo",
 "genre": "Rock",
 "display_category": "",
 "display_mood": "Sad",
 "is_new_track": false,
 "artist_channel_url": "/channel/UCnJoBJAmgihRWlyV5QgSujA",
 "display_genre": "Rock",
 "vid": "23c404ebcee1652c",
 "artist": "Josh Lippi & The Overtimers",
 "popularity_percentile": 99,
 "fp_ref_id": "23c404ebcee1652c",
 "category": "",
 "title": "St. Francis",
 "album": "None"
}