{
 "title": "Bare Feet Scuff Wood",
 "is_new_track": false,
 "artist": "None",
 "streamid": "cjmIPt-t0DfWtjR7WKbZjNJFjKOcnZAlh4RW-FEy8wFcyvrtuwwhHcMLvV4LEw1V",
 "artist_channel_url": null,
 "license_type": 0,
 "genre": "None",
 "vid": "2809043ee0a68fc1",
 "display_mood": null,
 "len": 33.983,
 "display_genre": "",
 "downloadable": true,
 "reference_vid": "2809043ee0a68fc1",
 "instruments": [],
 "category": "Foley",
 "mood": null,
 "download_url": "https://www.youtube.com/audiolibrary_download?vid=2809043ee0a68fc1",
 "waveform_url": "https://www.youtube.com/api/editor/waveform?expire=1579471200&if=0&scale=10&editlist=Cgh3YXZlZm9ybRocCOiBAhIWChAyODA5MDQzZWUwYTY4ZmMxEAAYAg%3D%3D&sigh=RCE9vFcqqhi56fYG31pE9g",
 "favorite": false,
 "fp_ref_id": "2809043ee0a68fc1",
 "album": "None",
 "popularity_percentile": 17,
 "track_url": "",
 "display_category": "Foley",
 "artist_url": ""
}