{
 "artist": "Kevin MacLeod, Syrinx Starr",
 "download_url": "https://www.youtube.com/audiolibrary_download?vid=35f21bd37c15d6d3",
 "waveform_url": "https://www.youtube.com/api/editor/waveform?expire=1579467600&if=0&scale=10&editlist=Cgh3YXZlZm9ybRocCPD1EhIWChAzNWYyMWJkMzdjMTVkNmQzEAAYAg%3D%3D&sigh=mZyeUguGgekYaoC0cUMdxg",
 "genre": "Dance & Electronic",
 "category": "",
 "is_new_track": false,
 "display_mood": "Bright",
 "album": "None",
 "track_url": "",
 "len": 310.933,
 "display_category": "",
 "favorite": false,
 "artist_channel_url": null,
 "vid": "35f21bd37c15d6d3",
 "streamid": "ZCC1jfFNZvUlq493nT9_ilh3qK4GABjJR1SKLyclZ8n531OyE-a-ZYCG0yld-XSM",
 "title": "The Big Beat 80s",
 "artist_url": "",
 "mood": "Bright",
 "downloadable": true,
 "display_genre": "Dance & Electronic",
 "popularity_percentile": 21,
 "reference_vid": "35f21bd37c15d6d3",
 "instruments": [
  "synth",
  "drums"
 ],
 "fp_ref_id": "35f21bd37c15d6d3",
 "license_type": 0
}