{
 "downloadable": true,
 "reference_vid": "47e4b12fa8f92ef6",
 "artist_channel_url": null,
 "is_new_track": false,
 "artist_url": "",
 "display_mood": null,
 "download_url": "https://www.youtube.com/audiolibrary_download?vid=47e4b12fa8f92ef6",
 "fp_ref_id": "47e4b12fa8f92ef6",
 "mood": null,
 "album": "None",
 "instruments": [],
 "len": 21.85,
 "waveform_url": "https://www.youtube.com/api/editor/waveform?expire=1579471200&if=0&scale=10&editlist=Cgh3YXZlZm9ybRocCIikARIWChA0N2U0YjEyZmE4ZjkyZWY2EAAYAg%3D%3D&sigh=bA2cJfeu4iLLwOu4TgHcBA",
 "streamid": "jnepmq0tRLsHOBYE2eKvkcTpCISBLdP0dlTFsvQ0pZ55LEsO_5yx6J1Rj-jR0HAH",
 "artist": "None",
 "popularity_percentile": 29,
 "title": "Muscle Car Start and Drive Away",
 "display_category": "Transportation",
 "display_genre": "",
 "license_type": 0,
 "vid": "47e4b12fa8f92ef6",
 "track_url": "",
 "genre": "None",
 "category": "Transportation",
 "favorite": false
}