{
 "artist": "Bad Snacks",
 "display_category": "",
 "genre": "R&B & Soul",
 "vid": "6a967273e37b9637",
 "instruments": [
  "drums",
  "electric piano",
  "synth",
  "electric guitar",
  "bass",
  "keys"
 ],
 "reference_vid": "6a967273e37b9637",
 "artist_url": "https://www.youtube.com/channel/UCBCI_QCAMe1hx8UNyvJlM_Q",
 "mood": "Romantic",
 "display_mood": "Romantic",
 "album": "None",
 "category": "",
 "license_type": 1,
 "display_genre": "R&B & Soul",
 "track_url": "",
 "artist_channel_url": "/channel/UCBCI_QCAMe1hx8UNyvJlM_Q",
 "fp_ref_id": "6a967273e37b9637",
 "download_url": "https://www.youtube.com/audiolibrary_download?vid=6a967273e37b9637",
 "is_new_track": false,
 "waveform_url": "https://www.youtube.com/api/editor/waveform?expire=1579467600&if=0&scale=10&editlist=Cgh3YXZlZm9ybRocCPi0CxIWChA2YTk2NzI3M2UzN2I5NjM3EAAYAg%3D%3D&sigh=P4nOOj3ptDzZrSFGHf86KA",
 "streamid": "8x_Tdd22xyhTGVvmU0gXbeH0mfK5Nkqr7Y3jWfCB2k_V8Ppg8n9jhdfJ0FFGg6xJ",
 "downloadable": true,
 "popularity_percentile": 99,
 "len": 187,
 "title": "Puppy Love",
 "favorite": false
}