{
 "artist_url": "",
 "favorite": false,
 "streamid": "O8WHGUb2dFxR3sakTiWD5LFApxICX7Sd9qWvSBgYX5lTH_2ziLZ7nIrhrexiVJjY",
 "download_url": "https://www.youtube.com/audiolibrary_download?vid=6d330c276b05411e",
 "waveform_url": "https://www.youtube.com/api/editor/waveform?expire=1579471200&if=0&scale=10&editlist=Cgh3YXZlZm9ybRobCLgXEhYKEDZkMzMwYzI3NmIwNTQxMWUQABgC&sigh=15gAEi0uR60ehApFBJY38g",
 "vid": "6d330c276b05411e",
 "display_category": "Foley",
 "title": "Run on grit",
 "album": "None",
 "mood": null,
 "artist_channel_url": null,
 "category": "Foley",
 "artist": "None",
 "downloadable": true,
 "is_new_track": false,
 "display_mood": null,
 "reference_vid": "6d330c276b05411e",
 "len": 3.85,
 "popularity_percentile": 44,
 "genre": "None",
 "fp_ref_id": "6d330c276b05411e",
 "track_url": "",
 "display_genre": "",
 "instruments": [],
 "license_type": 0
}