{
 "license_type": 0,
 "artist": "Silent Partner",
 "is_new_track": false,
 "fp_ref_id": "6fcd09f90fb4f9ec",
 "artist_channel_url": null,
 "len": 144.016,
 "downloadable": true,
 "display_mood": "Dark",
 "waveform_url": "https://www.youtube.com/api/editor/waveform?expire=1579467600&if=0&scale=10&editlist=Cgh3YXZlZm9ybRocCIDlCBIWChA2ZmNkMDlmOTBmYjRmOWVjEAAYAg%3D%3D&sigh=OCS8IETLFlXLjlAdnyqVfQ",
 "display_genre": "Dance & Electronic",
 "genre": "Dance & Electronic",
 "vid": "6fcd09f90fb4f9ec",
 "display_category": "",
 "reference_vid": "6fcd09f90fb4f9ec",
 "favorite": false,
 "download_url": "https://www.youtube.com/audiolibrary_download?vid=6fcd09f90fb4f9ec",
 "album": "None",
 "track_url": "",
 "streamid": "I6SAttVVi_T5M20-1z59lbH7z_01QQzvfv_bQ-Fa8CeO1QVj6xgRLMyeSspporpT",
 "mood": "Dark",
 "artist_url": "",
 "instruments": [
  "Drums",
  "Bass",
  "Piano",
  "Electric Guitar"
 ],
 "title": "Orientation",
 "popularity_percentile": 43,
 "category": ""
}