{
 "mood": null,
 "reference_vid": "78678bcfa3c235d3",
 "album": "None",
 "track_url": "",
 "waveform_url": "https://www.youtube.com/api/editor/waveform?expire=1579471200&if=0&scale=10&editlist=Cgh3YXZlZm9ybRobCOgHEhYKEDc4Njc4YmNmYTNjMjM1ZDMQABgC&sigh=6OgPLlW6fXJCKnV-PGxWEg",
 "display_mood": null,
 "title": "Air Woosh Underwater",
 "artist": "None",
 "is_new_track": false,
 "len": 1.15,
 "genre": "None",
 "display_genre": "",
 "downloadable": true,
 "display_category": "Water",
 "vid": "78678bcfa3c235d3",
 "popularity_percentile": 48,
 "download_url": "https://www.youtube.com/audiolibrary_download?vid=78678bcfa3c235d3",
 "favorite": false,
 "category": "Water",
 "artist_channel_url": null,
 "artist_url": "",
 "license_type": 0,
 "instruments": [],
 "fp_ref_id": "78678bcfa3c235d3",
 "streamid": "gwaQgybWiCQvMQjPpwQ4od3hKWJy47SnvD83a9yDMpcuwMSL4Z3JvWvzcga3riAp"
}