{
 "track_url": "",
 "download_url": "https://www.youtube.com/audiolibrary_download?vid=79100e44c826e2f7",
 "downloadable": true,
 "reference_vid": "79100e44c826e2f7",
 "mood": "Funky",
 "artist_url": "https://www.youtube.com/channel/UCL1zFMJb0sthwdAlGjGbdyg",
 "license_type": 1,
 "len": 148,
 "instruments": [
  "synths",
  "horns",
  "drums"
 ],
 "favorite": false,
 "waveform_url": "https://www.youtube.com/api/editor/waveform?expire=1579460400&if=0&scale=10&editlist=Cgh3YXZlZm9ybRocCKCECRIWChA3OTEwMGU0NGM4MjZlMmY3EAAYAg%3D%3D&sigh=UsPXGygorIHUDLx3AK7PKQ",
 "streamid": "CNYZirdmp51JROH_4Nh2c4gMBVDzzBARshWhS-h-aepiu_8fcSXKavyiAwwCVJpm",
 "genre": "Dance & Electronic",
 "display_category": "",
 "display_mood": "Funky",
 "is_new_track": false,
 "artist_channel_url": "/channel/UCL1zFMJb0sthwdAlGjGbdyg",
 "display_genre": "Dance & Electronic",
 "vid": "79100e44c826e2f7",
 "artist": "Quincas Moreira",
 "popularity_percentile": 99,
 "fp_ref_id": "79100e44c826e2f7",
 "category": "",
 "title": "Firefly",
 "album": "None"
}