{
 "vid": "b69db8aa3b89a3fb",
 "downloadable": true,
 "genre": "Dance & Electronic",
 "streamid": "bCQ0QqTZG10sOQfJEExUcyDl9PdmAKxoxt10JGxEL7Vk59pyVo60z30qFCf1lPVM",
 "favorite": false,
 "fp_ref_id": "b69db8aa3b89a3fb",
 "len": 169,
 "mood": "Dark",
 "display_category": "",
 "artist_url": "https://www.youtube.com/channel/UCcB_tnqYHwPzADwUdeppIIQ",
 "waveform_url": "https://www.youtube.com/api/editor/waveform?expire=1579467600&if=0&scale=10&editlist=Cgh3YXZlZm9ybRocCKioChIWChBiNjlkYjhhYTNiODlhM2ZiEAAYAg%3D%3D&sigh=Iry0JBStKQzSp-Ptjaiz5A",
 "display_mood": "Dark",
 "is_new_track": false,
 "reference_vid": "b69db8aa3b89a3fb",
 "title": "Open The Box",
 "artist": "Geographer",
 "track_url": "",
 "artist_channel_url": "/channel/UCcB_tnqYHwPzADwUdeppIIQ",
 "instruments": [
  "drums",
  "synth",
  "bass"
 ],
 "download_url": "https://www.youtube.com/audiolibrary_download?vid=b69db8aa3b89a3fb",
 "category": "",
 "display_genre": "Dance & Electronic",
 "popularity_percentile": 99,
 "album": "None",
 "license_type": 1
}