{
 "display_genre": "",
 "waveform_url": "https://www.youtube.com/api/editor/waveform?expire=1579471200&if=0&scale=10&editlist=Cgh3YXZlZm9ybRocCODCCRIWChBjNDNkMTc0YmJmYTlmODExEAAYAg%3D%3D&sigh=EuVSV0Z4HuMFaJpj5559Ww",
 "artist_url": "",
 "fp_ref_id": "c43d174bbfa9f811",
 "track_url": "",
 "license_type": 0,
 "display_category": "Weather",
 "album": "None",
 "vid": "c43d174bbfa9f811",
 "favorite": false,
 "is_new_track": false,
 "download_url": "https://www.youtube.com/audiolibrary_download?vid=c43d174bbfa9f811",
 "reference_vid": "c43d174bbfa9f811",
 "popularity_percentile": 77,
 "category": "Weather",
 "artist_channel_url": null,
 "mood": null,
 "streamid": "VsD9rcE8UPPZBOgoq4TP_fN5ymfTdyDAo3B92Ql7RlIboPGNPXNWcyMSMZBzfLKg",
 "len": 156.883,
 "genre": "None",
 "display_mood": null,
 "artist": "None",
 "downloadable": true,
 "title": "Wind In Leaves On Porch",
 "instruments": []
}