{
 "display_category": "Water",
 "genre": "None",
 "track_url": "",
 "is_new_track": false,
 "artist": "None",
 "title": "Sink Drain Far",
 "streamid": "etwfnEC6yw60dlE_9erPKk4yA2otvt8Ui-nC9gpgqnKzNz5QhqMP4RLdl4MgtECT",
 "downloadable": true,
 "album": "None",
 "fp_ref_id": "d1af92bb134ddc58",
 "len": 14.783,
 "favorite": false,
 "artist_channel_url": null,
 "display_mood": null,
 "download_url": "https://www.youtube.com/audiolibrary_download?vid=d1af92bb134ddc58",
 "artist_url": "",
 "instruments": [],
 "mood": null,
 "license_type": 0,
 "display_genre": "",
 "vid": "d1af92bb134ddc58",
 "waveform_url": "https://www.youtube.com/api/editor/waveform?expire=1579471200&if=0&scale=10&editlist=Cgh3YXZlZm9ybRobCLBtEhYKEGQxYWY5MmJiMTM0ZGRjNTgQABgC&sigh=FaGXb0hfg8RYcDrm6y-GWw",
 "reference_vid": "d1af92bb134ddc58",
 "category": "Water",
 "popularity_percentile": 82
}