{
 "downloadable": true,
 "waveform_url": "https://www.youtube.com/api/editor/waveform?expire=1579467600&if=0&scale=10&editlist=Cgh3YXZlZm9ybRocCNiJDxIWChBkNjM5ZjE2MTBhYWM2MTMyEAAYAg%3D%3D&sigh=G2YFmM-Ofyj8RaDHr8whcQ",
 "album": "None",
 "download_url": "https://www.youtube.com/audiolibrary_download?vid=d639f1610aac6132",
 "title": "Double Drift",
 "mood": "Dramatic",
 "display_mood": "Dramatic",
 "display_category": "",
 "track_url": "http://incompetech.com/music/royalty-free/index.html?isrc=USUAN1100254",
 "is_new_track": false,
 "reference_vid": "d639f1610aac6132",
 "license_type": 6,
 "artist": "Kevin MacLeod",
 "instruments": [
  "Drums",
  "Acoustic Guitar",
  "Bass",
  "Synth"
 ],
 "favorite": false,
 "fp_ref_id": "d639f1610aac6132",
 "display_genre": "Cinematic",
 "len": 247.75,
 "vid": "d639f1610aac6132",
 "category": "",
 "artist_url": "http://incompetech.com/",
 "popularity_percentile": 34,
 "genre": "Cinematic",
 "streamid": "yVmTPoFMJqvJTvmEDeToaqRoXNgAT0KY95xJYe5EHds6NhSZWpnO3Q1dClokezq4",
 "artist_channel_url": null
}