{
 "instruments": [
  "Drums",
  "Bass",
  "Electric Guitar"
 ],
 "album": "None",
 "artist": "Riot",
 "downloadable": true,
 "mood": "Bright",
 "display_mood": "Bright",
 "len": 158.916,
 "reference_vid": "decfeb2314de58a5",
 "fp_ref_id": "decfeb2314de58a5",
 "display_genre": "Rock",
 "display_category": "",
 "artist_channel_url": null,
 "artist_url": "",
 "track_url": "",
 "vid": "decfeb2314de58a5",
 "category": "",
 "title": "Silver",
 "genre": "Rock",
 "download_url": "https://www.youtube.com/audiolibrary_download?vid=decfeb2314de58a5",
 "favorite": false,
 "is_new_track": false,
 "waveform_url": "https://www.youtube.com/api/editor/waveform?expire=1579467600&if=0&scale=10&editlist=Cgh3YXZlZm9ybRocCLDSCRIWChBkZWNmZWIyMzE0ZGU1OGE1EAAYAg%3D%3D&sigh=y6WFAXQhHDH0sLK7rg2ioA",
 "license_type": 0,
 "popularity_percentile": 87,
 "streamid": "6K9qaGO9WzCYBm-09CUbu6LI_3AbRuKtI2uIuLhP93OdtvinQRlpWkQ6myC_mvKm"
}