{
 "display_genre": "Hip Hop & Rap",
 "streamid": "kqm9KHfGz3xIRKLzOUsJc7qdvYPG6lpyOGst69NxTC8nlNksKu1eMw72jNFkaLmd",
 "artist_channel_url": "/channel/UC6f69g5rtNFhix--ZY8yAFw",
 "display_category": "",
 "instruments": [
  "strings",
  "piano",
  "synth",
  "drums"
 ],
 "vid": "e5cc002fbf60cfcd",
 "genre": "Hip Hop & Rap",
 "waveform_url": "https://www.youtube.com/api/editor/waveform?expire=1579467600&if=0&scale=10&editlist=Cgh3YXZlZm9ybRocCMjBDBIWChBlNWNjMDAyZmJmNjBjZmNkEAAYAg%3D%3D&sigh=vwi6r21WsLyjkntyZdPjkg",
 "favorite": false,
 "is_new_track": false,
 "download_url": "https://www.youtube.com/audiolibrary_download?vid=e5cc002fbf60cfcd",
 "fp_ref_id": "e5cc002fbf60cfcd",
 "artist": "Anno Domini Beats",
 "category": "",
 "display_mood": "Dark",
 "len": 205,
 "track_url": "",
 "license_type": 1,
 "artist_url": "https://www.youtube.com/channel/UC6f69g5rtNFhix--ZY8yAFw",
 "downloadable": true,
 "popularity_percentile": 99,
 "reference_vid": "e5cc002fbf60cfcd",
 "mood": "Dark",
 "title": "Still Standing",
 "album": "None"
}