{
 "fp_ref_id": "ea08a2593baf8515",
 "reference_vid": "ea08a2593baf8515",
 "is_new_track": false,
 "download_url": "https://www.youtube.com/audiolibrary_download?vid=ea08a2593baf8515",
 "track_url": "",
 "artist_url": "https://www.youtube.com/channel/UCBCI_QCAMe1hx8UNyvJlM_Q",
 "license_type": 1,
 "streamid": "pIwH6pvta1ppdhM5wUIZN4-BQ1VW3TeKmJFE6WG7Tr-UbHPH6Io3CywS6FnuR6LQ",
 "genre": "R&B & Soul",
 "popularity_percentile": 99,
 "mood": "Calm",
 "downloadable": true,
 "vid": "ea08a2593baf8515",
 "len": 140,
 "instruments": [
  "bass",
  "synth",
  "violin",
  "strings",
  "drums",
  "percussion",
  "electric piano",
  "keys"
 ],
 "favorite": false,
 "display_genre": "R&B & Soul",
 "artist_channel_url": "/channel/UCBCI_QCAMe1hx8UNyvJlM_Q",
 "category": "",
 "artist": "Bad Snacks",
 "waveform_url": "https://www.youtube.com/api/editor/waveform?expire=1579467600&if=0&scale=10&editlist=Cgh3YXZlZm9ybRocCODFCBIWChBlYTA4YTI1OTNiYWY4NTE1EAAYAg%3D%3D&sigh=Ot3OgX5gcGx4RV2yZGEWuw",
 "display_mood": "Calm",
 "album": "None",
 "title": "Wallflowers",
 "display_category": ""
}