{
 "license_type": 0,
 "display_genre": "",
 "genre": "None",
 "download_url": "https://www.youtube.com/audiolibrary_download?vid=ec0e3c5feb9cc522",
 "artist_url": "",
 "downloadable": true,
 "len": 7.35,
 "album": "None",
 "mood": null,
 "artist": "None",
 "waveform_url": "https://www.youtube.com/api/editor/waveform?expire=1579471200&if=0&scale=10&editlist=Cgh3YXZlZm9ybRobCNg2EhYKEGVjMGUzYzVmZWI5Y2M1MjIQABgC&sigh=sduEUJUi6rfrXnxFvXZdtw",
 "artist_channel_url": null,
 "popularity_percentile": 93,
 "track_url": "",
 "display_category": "Office",
 "favorite": false,
 "fp_ref_id": "ec0e3c5feb9cc522",
 "title": "Click Continuous",
 "vid": "ec0e3c5feb9cc522",
 "display_mood": null,
 "reference_vid": "ec0e3c5feb9cc522",
 "instruments": [],
 "is_new_track": false,
 "streamid": "4ixdWlRgZrEy8z94DNBeQIyekXFbIMbChwAvY0eUmfTpIi40vmlyDADcqLVG9d-a",
 "category": "Office"
}