{
 "artist": "Huma-Huma",
 "mood": "Bright",
 "vid": "ef4b5e227f079e71",
 "streamid": "9d8midiZieQFowr5O8t2XpwaBfWcWwrcebH0cO0AZ66-fGr1W97iThpPKsq0wL4s",
 "display_category": "",
 "track_url": "",
 "artist_channel_url": null,
 "download_url": "https://www.youtube.com/audiolibrary_download?vid=ef4b5e227f079e71",
 "fp_ref_id": "ef4b5e227f079e71",
 "favorite": false,
 "waveform_url": "https://www.youtube.com/api/editor/waveform?expire=1579467600&if=0&scale=10&editlist=Cgh3YXZlZm9ybRocCODIBxIWChBlZjRiNWUyMjdmMDc5ZTcxEAAYAg%3D%3D&sigh=1v-K1K_MeJf8YHBPvmyC9A",
 "len": 124.216,
 "display_genre": "Alternative & Punk",
 "album": "None",
 "is_new_track": false,
 "genre": "Alternative & Punk",
 "reference_vid": "ef4b5e227f079e71",
 "title": "It's All Happening",
 "instruments": [
  "Electric Guitar",
  "Drums",
  "Bass"
 ],
 "artist_url": "",
 "category": "",
 "display_mood": "Bright",
 "popularity_percentile": 94,
 "downloadable": true,
 "license_type": 0
}