{
 "vid": "f9278524d92632e4",
 "downloadable": true,
 "genre": "Pop",
 "streamid": "nZxSVCNK6as6GXgH3vmMDIc2e5nXahhoP_Znv_arEFauoTGw1mVVStL-j2sVzxrE",
 "favorite": false,
 "fp_ref_id": "f9278524d92632e4",
 "len": 143,
 "mood": "Happy",
 "display_category": "",
 "artist_url": "https://www.youtube.com/channel/UCxfzyJ-HvEZbGmubAmfcsfQ",
 "waveform_url": "https://www.youtube.com/api/editor/waveform?expire=1579467600&if=0&scale=10&editlist=Cgh3YXZlZm9ybRocCJjdCBIWChBmOTI3ODUyNGQ5MjYzMmU0EAAYAg%3D%3D&sigh=vEF5tJAkig_DUuFce8oqiw",
 "display_mood": "Happy",
 "is_new_track": false,
 "reference_vid": "f9278524d92632e4",
 "title": "Tea for TWO",
 "artist": "The Whole Other",
 "track_url": "",
 "artist_channel_url": "/channel/UCxfzyJ-HvEZbGmubAmfcsfQ",
 "instruments": [
  "synth",
  "acoustic guitar",
  "bass",
  "drums",
  "keys"
 ],
 "download_url": "https://www.youtube.com/audiolibrary_download?vid=f9278524d92632e4",
 "category": "",
 "display_genre": "Pop",
 "popularity_percentile": 99,
 "album": "None",
 "license_type": 1
}